ceonstock/__init__.py
ceonstock/ceonstock_submission.py
ceonstock/config.py
ceonstock/errors.py
ceonstock/json_io_example.py
ceonstock/version.py
ceonstock/__json_io/__init__.py
ceonstock/__json_io/submission_input.py
ceonstock/_json_io/__init__.py
ceonstock/_json_io/_exporter.py
ceonstock/_json_io/_file_handler.py
ceonstock/_json_io/_file_loader.py
ceonstock/_json_io/_importer.py
ceonstock/_json_io/cstock_decoder.py
ceonstock/_json_io/cstock_encoder.py
ceonstock/_json_io/errors.py
ceonstock/_json_io/exporter.py
ceonstock/_json_io/importer.py
ceonstock/_render_server/_render_app.py
ceonstock/_render_server/_render_settings.py
ceonstock/_render_server/_render_task.py
ceonstock/_software_integrations/__init__.py
ceonstock/_software_integrations/houdini/__init__.py
ceonstock/_software_integrations/houdini/_hda_parm_maker.py
ceonstock/_software_integrations/houdini/_hda_ui_manager.py
ceonstock/_software_integrations/houdini/hda_ui_manager.py
ceonstock/_software_integrations/houdini/parm_maker/__init__.py
ceonstock/_software_integrations/houdini/parm_maker/color.py
ceonstock/_software_integrations/houdini/parm_maker/create.py
ceonstock/_software_integrations/houdini/parm_maker/hparms.py
ceonstock/_software_integrations/houdini/parm_maker/job_inputs.py
ceonstock/_software_integrations/houdini/parm_maker/parm_types.py
ceonstock/_submission_server/_actions.py
ceonstock/_submission_server/_submission.py
ceonstock/core/__init__.py
ceonstock/core/_render_task.py
ceonstock/core/base.py
ceonstock/core/file_action.py
ceonstock/core/file_reference.py
ceonstock/core/job.py
ceonstock/core/job_input.py
ceonstock/core/loader.py
ceonstock/core/project.py
ceonstock/core/project_input.py
ceonstock/core/render.py
ceonstock/core/submission_input.py
ceonstock/core/web_input.py
ceonstock/core/validator/__init__.py
ceonstock/core/validator/funcs.py
ceonstock/filesystem/__init__.py
ceonstock/filesystem/_dirs.py
ceonstock/filesystem/_errors.py
ceonstock/filesystem/_filesystem.py
ceonstock-0.2.7.dist-info/METADATA
ceonstock-0.2.7.dist-info/WHEEL
ceonstock-0.2.7.dist-info/top_level.txt
ceonstock-0.2.7.dist-info/RECORD
