Metadata-Version: 2.2
Name: ceonstock
Version: 0.2.7
Summary: Add your description here
Requires-Python: >=3.11
Requires-Dist: ceon-render>=0.2.1
